{"nodes": [{"id": "d_visual_studio_code_react_code_free_src_templates_arbol_madre_arbolscene_jsx", "label": "ArbolScene.jsx", "file_type": "code", "source_file": "D:\\Visual-Studio-Code\\React\\code-free\\src\\templates\\arbol-madre\\ArbolScene.jsx", "source_location": "L1"}, {"id": "arbol_madre_arbolscene_icontree", "label": "IconTree()", "file_type": "code", "source_file": "D:\\Visual-Studio-Code\\React\\code-free\\src\\templates\\arbol-madre\\ArbolScene.jsx", "source_location": "L6"}, {"id": "arbol_madre_arbolscene_iconreplay", "label": "IconReplay()", "file_type": "code", "source_file": "D:\\Visual-Studio-Code\\React\\code-free\\src\\templates\\arbol-madre\\ArbolScene.jsx", "source_location": "L14"}, {"id": "arbol_madre_arbolscene_iconfullscreen", "label": "IconFullscreen()", "file_type": "code", "source_file": "D:\\Visual-Studio-Code\\React\\code-free\\src\\templates\\arbol-madre\\ArbolScene.jsx", "source_location": "L21"}, {"id": "arbol_madre_arbolscene_iconleaf", "label": "IconLeaf()", "file_type": "code", "source_file": "D:\\Visual-Studio-Code\\React\\code-free\\src\\templates\\arbol-madre\\ArbolScene.jsx", "source_location": "L27"}, {"id": "arbol_madre_arbolscene_iconclose", "label": "IconClose()", "file_type": "code", "source_file": "D:\\Visual-Studio-Code\\React\\code-free\\src\\templates\\arbol-madre\\ArbolScene.jsx", "source_location": "L33"}, {"id": "arbol_madre_arbolscene_tema_bg", "label": "TEMA_BG", "file_type": "code", "source_file": "D:\\Visual-Studio-Code\\React\\code-free\\src\\templates\\arbol-madre\\ArbolScene.jsx", "source_location": "L40"}, {"id": "arbol_madre_arbolscene_tema_glow", "label": "TEMA_GLOW", "file_type": "code", "source_file": "D:\\Visual-Studio-Code\\React\\code-free\\src\\templates\\arbol-madre\\ArbolScene.jsx", "source_location": "L46"}, {"id": "arbol_madre_arbolscene_photo_titles", "label": "PHOTO_TITLES", "file_type": "code", "source_file": "D:\\Visual-Studio-Code\\React\\code-free\\src\\templates\\arbol-madre\\ArbolScene.jsx", "source_location": "L54"}, {"id": "arbol_madre_arbolscene_photo_messages", "label": "PHOTO_MESSAGES", "file_type": "code", "source_file": "D:\\Visual-Studio-Code\\React\\code-free\\src\\templates\\arbol-madre\\ArbolScene.jsx", "source_location": "L59"}, {"id": "arbol_madre_arbolscene_hashstring", "label": "hashString()", "file_type": "code", "source_file": "D:\\Visual-Studio-Code\\React\\code-free\\src\\templates\\arbol-madre\\ArbolScene.jsx", "source_location": "L72"}, {"id": "arbol_madre_arbolscene_mulberry32", "label": "mulberry32()", "file_type": "code", "source_file": "D:\\Visual-Studio-Code\\React\\code-free\\src\\templates\\arbol-madre\\ArbolScene.jsx", "source_location": "L81"}, {"id": "arbol_madre_arbolscene_shuffle", "label": "shuffle()", "file_type": "code", "source_file": "D:\\Visual-Studio-Code\\React\\code-free\\src\\templates\\arbol-madre\\ArbolScene.jsx", "source_location": "L90"}, {"id": "arbol_madre_arbolscene_builddisplayfotos", "label": "buildDisplayFotos()", "file_type": "code", "source_file": "D:\\Visual-Studio-Code\\React\\code-free\\src\\templates\\arbol-madre\\ArbolScene.jsx", "source_location": "L98"}, {"id": "arbol_madre_arbolscene_usetypewriter", "label": "useTypewriter()", "file_type": "code", "source_file": "D:\\Visual-Studio-Code\\React\\code-free\\src\\templates\\arbol-madre\\ArbolScene.jsx", "source_location": "L112"}, {"id": "arbol_madre_arbolscene_splashscreen", "label": "SplashScreen()", "file_type": "code", "source_file": "D:\\Visual-Studio-Code\\React\\code-free\\src\\templates\\arbol-madre\\ArbolScene.jsx", "source_location": "L135"}, {"id": "arbol_madre_arbolscene_arbolscene", "label": "ArbolScene()", "file_type": "code", "source_file": "D:\\Visual-Studio-Code\\React\\code-free\\src\\templates\\arbol-madre\\ArbolScene.jsx", "source_location": "L163"}, {"id": "arbol_madre_arbolscene_arbolview", "label": "ArbolView()", "file_type": "code", "source_file": "D:\\Visual-Studio-Code\\React\\code-free\\src\\templates\\arbol-madre\\ArbolScene.jsx", "source_location": "L209"}], "edges": [{"source": "d_visual_studio_code_react_code_free_src_templates_arbol_madre_arbolscene_jsx", "target": "react", "relation": "imports_from", "context": "import", "confidence": "EXTRACTED", "source_file": "D:\\Visual-Studio-Code\\React\\code-free\\src\\templates\\arbol-madre\\ArbolScene.jsx", "source_location": "L1", "weight": 1.0}, {"source": "d_visual_studio_code_react_code_free_src_templates_arbol_madre_arbolscene_jsx", "target": "d_visual_studio_code_react_code_free_src_templates_arbol_madre_usearbol_js", "relation": "imports_from", "context": "import", "confidence": "EXTRACTED", "source_file": "D:\\Visual-Studio-Code\\React\\code-free\\src\\templates\\arbol-madre\\ArbolScene.jsx", "source_location": "L2", "weight": 1.0}, {"source": "d_visual_studio_code_react_code_free_src_templates_arbol_madre_arbolscene_jsx", "target": "arbol_madre_usearbol_usearbol", "relation": "imports", "context": "import", "confidence": "EXTRACTED", "source_file": "D:\\Visual-Studio-Code\\React\\code-free\\src\\templates\\arbol-madre\\ArbolScene.jsx", "source_location": "L2", "weight": 1.0}, {"source": "d_visual_studio_code_react_code_free_src_templates_arbol_madre_arbolscene_jsx", "target": "d_visual_studio_code_react_code_free_src_templates_arbol_madre_arbol_css", "relation": "imports_from", "context": "import", "confidence": "EXTRACTED", "source_file": "D:\\Visual-Studio-Code\\React\\code-free\\src\\templates\\arbol-madre\\ArbolScene.jsx", "source_location": "L3", "weight": 1.0}, {"source": "d_visual_studio_code_react_code_free_src_templates_arbol_madre_arbolscene_jsx", "target": "arbol_madre_arbolscene_icontree", "relation": "contains", "confidence": "EXTRACTED", "source_file": "D:\\Visual-Studio-Code\\React\\code-free\\src\\templates\\arbol-madre\\ArbolScene.jsx", "source_location": "L6", "weight": 1.0}, {"source": "d_visual_studio_code_react_code_free_src_templates_arbol_madre_arbolscene_jsx", "target": "arbol_madre_arbolscene_iconreplay", "relation": "contains", "confidence": "EXTRACTED", "source_file": "D:\\Visual-Studio-Code\\React\\code-free\\src\\templates\\arbol-madre\\ArbolScene.jsx", "source_location": "L14", "weight": 1.0}, {"source": "d_visual_studio_code_react_code_free_src_templates_arbol_madre_arbolscene_jsx", "target": "arbol_madre_arbolscene_iconfullscreen", "relation": "contains", "confidence": "EXTRACTED", "source_file": "D:\\Visual-Studio-Code\\React\\code-free\\src\\templates\\arbol-madre\\ArbolScene.jsx", "source_location": "L21", "weight": 1.0}, {"source": "d_visual_studio_code_react_code_free_src_templates_arbol_madre_arbolscene_jsx", "target": "arbol_madre_arbolscene_iconleaf", "relation": "contains", "confidence": "EXTRACTED", "source_file": "D:\\Visual-Studio-Code\\React\\code-free\\src\\templates\\arbol-madre\\ArbolScene.jsx", "source_location": "L27", "weight": 1.0}, {"source": "d_visual_studio_code_react_code_free_src_templates_arbol_madre_arbolscene_jsx", "target": "arbol_madre_arbolscene_iconclose", "relation": "contains", "confidence": "EXTRACTED", "source_file": "D:\\Visual-Studio-Code\\React\\code-free\\src\\templates\\arbol-madre\\ArbolScene.jsx", "source_location": "L33", "weight": 1.0}, {"source": "d_visual_studio_code_react_code_free_src_templates_arbol_madre_arbolscene_jsx", "target": "arbol_madre_arbolscene_tema_bg", "relation": "contains", "confidence": "EXTRACTED", "source_file": "D:\\Visual-Studio-Code\\React\\code-free\\src\\templates\\arbol-madre\\ArbolScene.jsx", "source_location": "L40", "weight": 1.0}, {"source": "d_visual_studio_code_react_code_free_src_templates_arbol_madre_arbolscene_jsx", "target": "arbol_madre_arbolscene_tema_glow", "relation": "contains", "confidence": "EXTRACTED", "source_file": "D:\\Visual-Studio-Code\\React\\code-free\\src\\templates\\arbol-madre\\ArbolScene.jsx", "source_location": "L46", "weight": 1.0}, {"source": "d_visual_studio_code_react_code_free_src_templates_arbol_madre_arbolscene_jsx", "target": "arbol_madre_arbolscene_photo_titles", "relation": "contains", "confidence": "EXTRACTED", "source_file": "D:\\Visual-Studio-Code\\React\\code-free\\src\\templates\\arbol-madre\\ArbolScene.jsx", "source_location": "L54", "weight": 1.0}, {"source": "d_visual_studio_code_react_code_free_src_templates_arbol_madre_arbolscene_jsx", "target": "arbol_madre_arbolscene_photo_messages", "relation": "contains", "confidence": "EXTRACTED", "source_file": "D:\\Visual-Studio-Code\\React\\code-free\\src\\templates\\arbol-madre\\ArbolScene.jsx", "source_location": "L59", "weight": 1.0}, {"source": "d_visual_studio_code_react_code_free_src_templates_arbol_madre_arbolscene_jsx", "target": "arbol_madre_arbolscene_hashstring", "relation": "contains", "confidence": "EXTRACTED", "source_file": "D:\\Visual-Studio-Code\\React\\code-free\\src\\templates\\arbol-madre\\ArbolScene.jsx", "source_location": "L72", "weight": 1.0}, {"source": "d_visual_studio_code_react_code_free_src_templates_arbol_madre_arbolscene_jsx", "target": "arbol_madre_arbolscene_mulberry32", "relation": "contains", "confidence": "EXTRACTED", "source_file": "D:\\Visual-Studio-Code\\React\\code-free\\src\\templates\\arbol-madre\\ArbolScene.jsx", "source_location": "L81", "weight": 1.0}, {"source": "d_visual_studio_code_react_code_free_src_templates_arbol_madre_arbolscene_jsx", "target": "arbol_madre_arbolscene_shuffle", "relation": "contains", "confidence": "EXTRACTED", "source_file": "D:\\Visual-Studio-Code\\React\\code-free\\src\\templates\\arbol-madre\\ArbolScene.jsx", "source_location": "L90", "weight": 1.0}, {"source": "d_visual_studio_code_react_code_free_src_templates_arbol_madre_arbolscene_jsx", "target": "arbol_madre_arbolscene_builddisplayfotos", "relation": "contains", "confidence": "EXTRACTED", "source_file": "D:\\Visual-Studio-Code\\React\\code-free\\src\\templates\\arbol-madre\\ArbolScene.jsx", "source_location": "L98", "weight": 1.0}, {"source": "d_visual_studio_code_react_code_free_src_templates_arbol_madre_arbolscene_jsx", "target": "arbol_madre_arbolscene_usetypewriter", "relation": "contains", "confidence": "EXTRACTED", "source_file": "D:\\Visual-Studio-Code\\React\\code-free\\src\\templates\\arbol-madre\\ArbolScene.jsx", "source_location": "L112", "weight": 1.0}, {"source": "d_visual_studio_code_react_code_free_src_templates_arbol_madre_arbolscene_jsx", "target": "arbol_madre_arbolscene_splashscreen", "relation": "contains", "confidence": "EXTRACTED", "source_file": "D:\\Visual-Studio-Code\\React\\code-free\\src\\templates\\arbol-madre\\ArbolScene.jsx", "source_location": "L135", "weight": 1.0}, {"source": "d_visual_studio_code_react_code_free_src_templates_arbol_madre_arbolscene_jsx", "target": "arbol_madre_arbolscene_arbolscene", "relation": "contains", "confidence": "EXTRACTED", "source_file": "D:\\Visual-Studio-Code\\React\\code-free\\src\\templates\\arbol-madre\\ArbolScene.jsx", "source_location": "L163", "weight": 1.0}, {"source": "d_visual_studio_code_react_code_free_src_templates_arbol_madre_arbolscene_jsx", "target": "arbol_madre_arbolscene_arbolview", "relation": "contains", "confidence": "EXTRACTED", "source_file": "D:\\Visual-Studio-Code\\React\\code-free\\src\\templates\\arbol-madre\\ArbolScene.jsx", "source_location": "L209", "weight": 1.0}, {"source": "arbol_madre_arbolscene_builddisplayfotos", "target": "arbol_madre_arbolscene_hashstring", "relation": "calls", "context": "call", "confidence": "EXTRACTED", "source_file": "D:\\Visual-Studio-Code\\React\\code-free\\src\\templates\\arbol-madre\\ArbolScene.jsx", "source_location": "L106", "weight": 1.0}, {"source": "arbol_madre_arbolscene_builddisplayfotos", "target": "arbol_madre_arbolscene_mulberry32", "relation": "calls", "context": "call", "confidence": "EXTRACTED", "source_file": "D:\\Visual-Studio-Code\\React\\code-free\\src\\templates\\arbol-madre\\ArbolScene.jsx", "source_location": "L107", "weight": 1.0}, {"source": "arbol_madre_arbolscene_builddisplayfotos", "target": "arbol_madre_arbolscene_shuffle", "relation": "calls", "context": "call", "confidence": "EXTRACTED", "source_file": "D:\\Visual-Studio-Code\\React\\code-free\\src\\templates\\arbol-madre\\ArbolScene.jsx", "source_location": "L108", "weight": 1.0}, {"source": "arbol_madre_arbolscene_arbolview", "target": "arbol_madre_arbolscene_usetypewriter", "relation": "calls", "context": "call", "confidence": "EXTRACTED", "source_file": "D:\\Visual-Studio-Code\\React\\code-free\\src\\templates\\arbol-madre\\ArbolScene.jsx", "source_location": "L223", "weight": 1.0}], "raw_calls": [{"caller_nid": "arbol_madre_arbolscene_hashstring", "callee": "charCodeAt", "is_member_call": true, "source_file": "D:\\Visual-Studio-Code\\React\\code-free\\src\\templates\\arbol-madre\\ArbolScene.jsx", "source_location": "L75"}, {"caller_nid": "arbol_madre_arbolscene_hashstring", "callee": "imul", "is_member_call": true, "source_file": "D:\\Visual-Studio-Code\\React\\code-free\\src\\templates\\arbol-madre\\ArbolScene.jsx", "source_location": "L76"}, {"caller_nid": "arbol_madre_arbolscene_mulberry32", "callee": "imul", "is_member_call": true, "source_file": "D:\\Visual-Studio-Code\\React\\code-free\\src\\templates\\arbol-madre\\ArbolScene.jsx", "source_location": "L84"}, {"caller_nid": "arbol_madre_arbolscene_mulberry32", "callee": "imul", "is_member_call": true, "source_file": "D:\\Visual-Studio-Code\\React\\code-free\\src\\templates\\arbol-madre\\ArbolScene.jsx", "source_location": "L85"}, {"caller_nid": "arbol_madre_arbolscene_shuffle", "callee": "floor", "is_member_call": true, "source_file": "D:\\Visual-Studio-Code\\React\\code-free\\src\\templates\\arbol-madre\\ArbolScene.jsx", "source_location": "L92"}, {"caller_nid": "arbol_madre_arbolscene_shuffle", "callee": "rand", "is_member_call": false, "source_file": "D:\\Visual-Studio-Code\\React\\code-free\\src\\templates\\arbol-madre\\ArbolScene.jsx", "source_location": "L92"}, {"caller_nid": "arbol_madre_arbolscene_builddisplayfotos", "callee": "isArray", "is_member_call": true, "source_file": "D:\\Visual-Studio-Code\\React\\code-free\\src\\templates\\arbol-madre\\ArbolScene.jsx", "source_location": "L99"}, {"caller_nid": "arbol_madre_arbolscene_builddisplayfotos", "callee": "slice", "is_member_call": true, "source_file": "D:\\Visual-Studio-Code\\React\\code-free\\src\\templates\\arbol-madre\\ArbolScene.jsx", "source_location": "L99"}, {"caller_nid": "arbol_madre_arbolscene_builddisplayfotos", "callee": "push", "is_member_call": true, "source_file": "D:\\Visual-Studio-Code\\React\\code-free\\src\\templates\\arbol-madre\\ArbolScene.jsx", "source_location": "L103"}, {"caller_nid": "arbol_madre_arbolscene_builddisplayfotos", "callee": "join", "is_member_call": true, "source_file": "D:\\Visual-Studio-Code\\React\\code-free\\src\\templates\\arbol-madre\\ArbolScene.jsx", "source_location": "L106"}, {"caller_nid": "arbol_madre_arbolscene_usetypewriter", "callee": "useState", "is_member_call": false, "source_file": "D:\\Visual-Studio-Code\\React\\code-free\\src\\templates\\arbol-madre\\ArbolScene.jsx", "source_location": "L113"}, {"caller_nid": "arbol_madre_arbolscene_usetypewriter", "callee": "useState", "is_member_call": false, "source_file": "D:\\Visual-Studio-Code\\React\\code-free\\src\\templates\\arbol-madre\\ArbolScene.jsx", "source_location": "L114"}, {"caller_nid": "arbol_madre_arbolscene_usetypewriter", "callee": "useRef", "is_member_call": false, "source_file": "D:\\Visual-Studio-Code\\React\\code-free\\src\\templates\\arbol-madre\\ArbolScene.jsx", "source_location": "L115"}, {"caller_nid": "arbol_madre_arbolscene_usetypewriter", "callee": "useEffect", "is_member_call": false, "source_file": "D:\\Visual-Studio-Code\\React\\code-free\\src\\templates\\arbol-madre\\ArbolScene.jsx", "source_location": "L117"}, {"caller_nid": "arbol_madre_arbolscene_arbolscene", "callee": "useState", "is_member_call": false, "source_file": "D:\\Visual-Studio-Code\\React\\code-free\\src\\templates\\arbol-madre\\ArbolScene.jsx", "source_location": "L164"}, {"caller_nid": "arbol_madre_arbolscene_arbolscene", "callee": "replace", "is_member_call": true, "source_file": "D:\\Visual-Studio-Code\\React\\code-free\\src\\templates\\arbol-madre\\ArbolScene.jsx", "source_location": "L173"}, {"caller_nid": "arbol_madre_arbolscene_arbolview", "callee": "useRef", "is_member_call": false, "source_file": "D:\\Visual-Studio-Code\\React\\code-free\\src\\templates\\arbol-madre\\ArbolScene.jsx", "source_location": "L210"}, {"caller_nid": "arbol_madre_arbolscene_arbolview", "callee": "useState", "is_member_call": false, "source_file": "D:\\Visual-Studio-Code\\React\\code-free\\src\\templates\\arbol-madre\\ArbolScene.jsx", "source_location": "L211"}, {"caller_nid": "arbol_madre_arbolscene_arbolview", "callee": "isArray", "is_member_call": true, "source_file": "D:\\Visual-Studio-Code\\React\\code-free\\src\\templates\\arbol-madre\\ArbolScene.jsx", "source_location": "L213"}, {"caller_nid": "arbol_madre_arbolscene_arbolview", "callee": "join", "is_member_call": true, "source_file": "D:\\Visual-Studio-Code\\React\\code-free\\src\\templates\\arbol-madre\\ArbolScene.jsx", "source_location": "L213"}, {"caller_nid": "arbol_madre_arbolscene_arbolview", "callee": "useMemo", "is_member_call": false, "source_file": "D:\\Visual-Studio-Code\\React\\code-free\\src\\templates\\arbol-madre\\ArbolScene.jsx", "source_location": "L215"}, {"caller_nid": "arbol_madre_arbolscene_arbolview", "callee": "useRef", "is_member_call": false, "source_file": "D:\\Visual-Studio-Code\\React\\code-free\\src\\templates\\arbol-madre\\ArbolScene.jsx", "source_location": "L225"}, {"caller_nid": "arbol_madre_arbolscene_arbolview", "callee": "useEffect", "is_member_call": false, "source_file": "D:\\Visual-Studio-Code\\React\\code-free\\src\\templates\\arbol-madre\\ArbolScene.jsx", "source_location": "L226"}, {"caller_nid": "arbol_madre_arbolscene_arbolview", "callee": "useMemo", "is_member_call": false, "source_file": "D:\\Visual-Studio-Code\\React\\code-free\\src\\templates\\arbol-madre\\ArbolScene.jsx", "source_location": "L230"}, {"caller_nid": "arbol_madre_arbolscene_arbolview", "callee": "useArbol", "is_member_call": false, "source_file": "D:\\Visual-Studio-Code\\React\\code-free\\src\\templates\\arbol-madre\\ArbolScene.jsx", "source_location": "L236"}, {"caller_nid": "arbol_madre_arbolscene_arbolview", "callee": "max", "is_member_call": true, "source_file": "D:\\Visual-Studio-Code\\React\\code-free\\src\\templates\\arbol-madre\\ArbolScene.jsx", "source_location": "L281"}]}